[{"type":"Feature","properties":[{"gid":"245"},{"co_cnes":"7693842"},{"lat":"0.941182363681184"},{"long":"-60.4192766547203"},{"no_fantasia":"UNIDADE BASICA DE SAUDE GENTIL CARNEIRO BRITO"},{"no_logradouro":"VICINAL 01"},{"nu_endereco":"S/N"},{"no_bairro":"CONJUNTO GENTIL"},{"nu_telefone":"9532381926"},{"co_cep":"69373000"},{"uf":"RR"},{"cidade":"Rorainópolis"},{"ano_ubs_det":"2016"},{"mes_ubs_det":"5"}],"geometry":{"type":"Point","coordinates":[-60.41927665472,0.94118236368118]}},{"type":"Feature","properties":[{"gid":"347"},{"co_cnes":"2590107"},{"lat":"2.61"},{"long":"-60.597"},{"no_fantasia":"POSTO DE SAUDE CONFIANCA III VILA CENTRAL"},{"no_logradouro":"BR"},{"nu_endereco":"S/N"},{"no_bairro":"CENTRO"},{"nu_telefone":""},{"co_cep":"69390000"},{"uf":"RR"},{"cidade":"Cantá"},{"ano_ubs_det":"2016"},{"mes_ubs_det":"5"}],"geometry":{"type":"Point","coordinates":[-60.597,2.61]}},{"type":"Feature","properties":[{"gid":"95"},{"co_cnes":"2476657"},{"lat":"1.80387124729759"},{"long":"-61.14917687013"},{"no_fantasia":"CENTRO DE SAUDE MANOEL LUIZ RODRIGUES"},{"no_logradouro":"PRACA PE CALLERI"},{"nu_endereco":"S/N"},{"no_bairro":"CENTRO"},{"nu_telefone":"(95)5321226"},{"co_cep":"69360000"},{"uf":"RR"},{"cidade":"Caracaraí"},{"ano_ubs_det":"2016"},{"mes_ubs_det":"5"}],"geometry":{"type":"Point","coordinates":[-61.14917687013,1.8038712472976]}},{"type":"Feature","properties":[{"gid":"28673"},{"co_cnes":"2476754"},{"lat":"0.937195393597556"},{"long":"-60.4250604939819"},{"no_fantasia":"CENTRO DE SAUDE DRA MARIA YANDARA"},{"no_logradouro":"AV DRA YANDARA"},{"nu_endereco":"S/N"},{"no_bairro":"CENTRO"},{"nu_telefone":"(95)32381926"},{"co_cep":"69373000"},{"uf":"RR"},{"cidade":"Rorainópolis"},{"ano_ubs_det":"2016"},{"mes_ubs_det":"5"}],"geometry":{"type":"Point","coordinates":[-60.425060493982,0.93719539359756]}},{"type":"Feature","properties":[{"gid":"440"},{"co_cnes":"2589796"},{"lat":"3.28819513320913"},{"long":"-61.0916662216169"},{"no_fantasia":"POSTO DE SAUDE DO TAIANO"},{"no_logradouro":"RUA A"},{"nu_endereco":"S/N"},{"no_bairro":"ZONA RURAL"},{"nu_telefone":""},{"co_cep":"69350000"},{"uf":"RR"},{"cidade":"Alto Alegre"},{"ano_ubs_det":"2016"},{"mes_ubs_det":"5"}],"geometry":{"type":"Point","coordinates":[-61.091666221617,3.2881951332091]}},{"type":"Feature","properties":[{"gid":"1193"},{"co_cnes":"6895107"},{"lat":"2.44984271639733"},{"long":"-60.9201952815056"},{"no_fantasia":"POSTO DE SAUDE J FLORES"},{"no_logradouro":"AVENIDA MARANHAO"},{"nu_endereco":"S/N"},{"no_bairro":"J FLORES"},{"nu_telefone":""},{"co_cep":"69340000"},{"uf":"RR"},{"cidade":"Mucajaí"},{"ano_ubs_det":"2016"},{"mes_ubs_det":"5"}],"geometry":{"type":"Point","coordinates":[-60.920195281506,2.4498427163973]}},{"type":"Feature","properties":[{"gid":"2337"},{"co_cnes":"7013337"},{"lat":"2.82381767149849"},{"long":"-60.7567119598389"},{"no_fantasia":"UNIDADE BASICA DE SAUDE JORGE ANDRE GURJAO VIEIRA"},{"no_logradouro":"RUA CC 24"},{"nu_endereco":"S/N"},{"no_bairro":"CONJUNTO CIDADAO"},{"nu_telefone":"3625-2700"},{"co_cep":"69301970"},{"uf":"RR"},{"cidade":"Boa Vista"},{"ano_ubs_det":"2016"},{"mes_ubs_det":"5"}],"geometry":{"type":"Point","coordinates":[-60.756711959839,2.8238176714985]}},{"type":"Feature","properties":[{"gid":"2160"},{"co_cnes":"2744554"},{"lat":"2.82535314559928"},{"long":"-60.6625986099226"},{"no_fantasia":"UNIDADE BASICA DE SAUDE IONE SANTIAGO"},{"no_logradouro":"RUA PRESIDENTE COSTA E SILVA"},{"nu_endereco":"356"},{"no_bairro":"SAO PEDRO"},{"nu_telefone":"(95)3623 2200"},{"co_cep":"69301970"},{"uf":"RR"},{"cidade":"Boa Vista"},{"ano_ubs_det":"2016"},{"mes_ubs_det":"5"}],"geometry":{"type":"Point","coordinates":[-60.662598609923,2.8253531455993]}},{"type":"Feature","properties":[{"gid":"2407"},{"co_cnes":"6814581"},{"lat":"2.16625928878778"},{"long":"-61.0512828826887"},{"no_fantasia":"UNIDADE BASICA DE SAUDE FRANCISCO DA SILVA"},{"no_logradouro":"RUA JANIO QUADROS"},{"nu_endereco":"S/N"},{"no_bairro":"CENTRO"},{"nu_telefone":""},{"co_cep":"69348000"},{"uf":"RR"},{"cidade":"Iracema"},{"ano_ubs_det":"2016"},{"mes_ubs_det":"5"}],"geometry":{"type":"Point","coordinates":[-61.051282882689,2.1662592887878]}},{"type":"Feature","properties":[{"gid":"3988"},{"co_cnes":"2476754"},{"lat":"0.937195393597556"},{"long":"-60.4250604939819"},{"no_fantasia":"CENTRO DE SAUDE DRA MARIA YANDARA"},{"no_logradouro":"AV DRA YANDARA"},{"nu_endereco":"S/N"},{"no_bairro":"CENTRO"},{"nu_telefone":"(95)32381926"},{"co_cep":"69373000"},{"uf":"RR"},{"cidade":"Rorainópolis"},{"ano_ubs_det":"2016"},{"mes_ubs_det":"5"}],"geometry":{"type":"Point","coordinates":[-60.425060493982,0.93719539359756]}},{"type":"Feature","properties":[{"gid":"3645"},{"co_cnes":"2320568"},{"lat":"4.47525934021225"},{"long":"-61.1473063471493"},{"no_fantasia":"UNIDADE DE REFERENCIA DE SAUDE DA FAMILIA"},{"no_logradouro":"MONTE RORAIMA"},{"nu_endereco":"S/N"},{"no_bairro":"VILA NOVA"},{"nu_telefone":""},{"co_cep":"69345000"},{"uf":"RR"},{"cidade":"Pacaraima"},{"ano_ubs_det":"2016"},{"mes_ubs_det":"5"}],"geometry":{"type":"Point","coordinates":[-61.147306347149,4.4752593402122]}},{"type":"Feature","properties":[{"gid":"4049"},{"co_cnes":"7022468"},{"lat":"4.60140715550127"},{"long":"-60.1616477966309"},{"no_fantasia":"UNIDADE BASICA DE SAUDE DAVID CAVALCANTE DE LIMA"},{"no_logradouro":"CECI MOTA"},{"nu_endereco":"S/N"},{"no_bairro":"VENEZUELA"},{"nu_telefone":""},{"co_cep":"69358000"},{"uf":"RR"},{"cidade":"Uiramutã"},{"ano_ubs_det":"2016"},{"mes_ubs_det":"5"}],"geometry":{"type":"Point","coordinates":[-60.161647796631,4.6014071555013]}},{"type":"Feature","properties":[{"gid":"4210"},{"co_cnes":"7013337"},{"lat":"2.82381767149849"},{"long":"-60.7567119598389"},{"no_fantasia":"UNIDADE BASICA DE SAUDE JORGE ANDRE GURJAO VIEIRA"},{"no_logradouro":"RUA CC 24"},{"nu_endereco":"S/N"},{"no_bairro":"CONJUNTO CIDADAO"},{"nu_telefone":"3625-2700"},{"co_cep":"69301970"},{"uf":"RR"},{"cidade":"Boa Vista"},{"ano_ubs_det":"2016"},{"mes_ubs_det":"5"}],"geometry":{"type":"Point","coordinates":[-60.756711959839,2.8238176714985]}},{"type":"Feature","properties":[{"gid":"4713"},{"co_cnes":"2476746"},{"lat":"0.937195393597556"},{"long":"-60.4250604939819"},{"no_fantasia":"UNIDADE BASICA DE SAUDE ANTONIO CARLOS PEREIRA"},{"no_logradouro":"AV 7 DE SETEMBRO"},{"nu_endereco":"S/N"},{"no_bairro":"CENTRO"},{"nu_telefone":"(95)2381926"},{"co_cep":"69373000"},{"uf":"RR"},{"cidade":"Rorainópolis"},{"ano_ubs_det":"2016"},{"mes_ubs_det":"5"}],"geometry":{"type":"Point","coordinates":[-60.425060493982,0.93719539359756]}},{"type":"Feature","properties":[{"gid":"5155"},{"co_cnes":"2566605"},{"lat":"2.79294133186332"},{"long":"-60.7416272163373"},{"no_fantasia":"UNIDADE BASICA DE SAUDE SENADOR HELIO CAMPOS"},{"no_logradouro":"RUA PEDRO ALDEMAR BANTI"},{"nu_endereco":"28"},{"no_bairro":"SENADOR HELIO CAMPOS"},{"nu_telefone":"(95) 3621-6056"},{"co_cep":"69301970"},{"uf":"RR"},{"cidade":"Boa Vista"},{"ano_ubs_det":"2016"},{"mes_ubs_det":"5"}],"geometry":{"type":"Point","coordinates":[-60.741627216337,2.7929413318633]}},{"type":"Feature","properties":[{"gid":"5139"},{"co_cnes":"2319918"},{"lat":"2.7496933937072"},{"long":"-61.1898350715619"},{"no_fantasia":"POSTO DE SAUDE VILA SAO SILVESTRE"},{"no_logradouro":"RUA PRINCIPAL"},{"nu_endereco":"S/N"},{"no_bairro":"CENTRO"},{"nu_telefone":""},{"co_cep":"69350000"},{"uf":"RR"},{"cidade":"Alto Alegre"},{"ano_ubs_det":"2016"},{"mes_ubs_det":"5"}],"geometry":{"type":"Point","coordinates":[-61.189835071562,2.7496933937072]}},{"type":"Feature","properties":[{"gid":"5477"},{"co_cnes":"2320894"},{"lat":"2.47977223505342"},{"long":"-60.9115185306216"},{"no_fantasia":"CENTRO DE SAUDE EDITE CARDOSO"},{"no_logradouro":"RUA RUFINO DE SOUSA"},{"nu_endereco":"S/N"},{"no_bairro":"CENTRO"},{"nu_telefone":""},{"co_cep":"69340000"},{"uf":"RR"},{"cidade":"Mucajaí"},{"ano_ubs_det":"2016"},{"mes_ubs_det":"5"}],"geometry":{"type":"Point","coordinates":[-60.911518530622,2.4797722350534]}},{"type":"Feature","properties":[{"gid":"6124"},{"co_cnes":"2744570"},{"lat":"2.81668191910439"},{"long":"-60.670532672965"},{"no_fantasia":"UNIDADE BASICA DE SAUDE DR SILVIO LOFEGO BOTELHO"},{"no_logradouro":"AV MINAS GERAIS"},{"nu_endereco":"512"},{"no_bairro":"DOS ESTADOS"},{"nu_telefone":"(95)36238714"},{"co_cep":"69301000"},{"uf":"RR"},{"cidade":"Boa Vista"},{"ano_ubs_det":"2016"},{"mes_ubs_det":"5"}],"geometry":{"type":"Point","coordinates":[-60.670532672965,2.8166819191044]}},{"type":"Feature","properties":[{"gid":"6079"},{"co_cnes":"2476681"},{"lat":"1.22423529624935"},{"long":"-60.390000343321"},{"no_fantasia":"CENTRO DE SAUDE NOVO PARAISO"},{"no_logradouro":"BR 174"},{"nu_endereco":"S/N"},{"no_bairro":"INTERIOR"},{"nu_telefone":""},{"co_cep":"69360000"},{"uf":"RR"},{"cidade":"Caracaraí"},{"ano_ubs_det":"2016"},{"mes_ubs_det":"5"}],"geometry":{"type":"Point","coordinates":[-60.390000343321,1.2242352962493]}},{"type":"Feature","properties":[{"gid":"6648"},{"co_cnes":"2566753"},{"lat":"2.81668191910439"},{"long":"-60.670532672965"},{"no_fantasia":"UNIDADE BASICA DE SAUDE CARANA"},{"no_logradouro":"RUA VALMIR PEREIRA DA ROCHA"},{"nu_endereco":"98"},{"no_bairro":"CARANA"},{"nu_telefone":"(95) 36267499"},{"co_cep":"69313620"},{"uf":"RR"},{"cidade":"Boa Vista"},{"ano_ubs_det":"2016"},{"mes_ubs_det":"5"}],"geometry":{"type":"Point","coordinates":[-60.670532672965,2.8166819191044]}},{"type":"Feature","properties":[{"gid":"6668"},{"co_cnes":"2320088"},{"lat":"3.36"},{"long":"-59.833"},{"no_fantasia":"UBS NOVA ESPERANCA"},{"no_logradouro":"RUA PRINCIPAL"},{"nu_endereco":"S/N"},{"no_bairro":"VILA NOVA ESPERANCA"},{"nu_telefone":"(95)36231O36"},{"co_cep":"69380000"},{"uf":"RR"},{"cidade":"Bonfim"},{"ano_ubs_det":"2016"},{"mes_ubs_det":"5"}],"geometry":{"type":"Point","coordinates":[-59.833,3.36]}},{"type":"Feature","properties":[{"gid":"6611"},{"co_cnes":"2744465"},{"lat":"2.81668191910439"},{"long":"-60.670532672965"},{"no_fantasia":"UNIDADE BASICA DE SAUDE ASA BRANCA"},{"no_logradouro":"RUA FRANCISCO CUSTODIO DE ANDRADE"},{"nu_endereco":"505"},{"no_bairro":"ASA BRANCA"},{"nu_telefone":"(95)3626 1754"},{"co_cep":"69312258"},{"uf":"RR"},{"cidade":"Boa Vista"},{"ano_ubs_det":"2016"},{"mes_ubs_det":"5"}],"geometry":{"type":"Point","coordinates":[-60.670532672965,2.8166819191044]}},{"type":"Feature","properties":[{"gid":"7145"},{"co_cnes":"2320762"},{"lat":"2.1800283"},{"long":"-61.039992"},{"no_fantasia":"UNIDADE MISTA IRMA CAMILA"},{"no_logradouro":"RUA HELOI PEREIRA"},{"nu_endereco":"S/N"},{"no_bairro":"CENTRO"},{"nu_telefone":"(95)35431132"},{"co_cep":"69348000"},{"uf":"RR"},{"cidade":"Iracema"},{"ano_ubs_det":"2016"},{"mes_ubs_det":"5"}],"geometry":{"type":"Point","coordinates":[-61.039992,2.1800283]}},{"type":"Feature","properties":[{"gid":"7634"},{"co_cnes":"2566265"},{"lat":"2.83406496047965"},{"long":"-60.7011580467207"},{"no_fantasia":"UNIDADE BASICA DE SAUDE JARDIM FLORESTA"},{"no_logradouro":"RUA ANA CECILIA MOTA DA SILVA"},{"nu_endereco":"S/N"},{"no_bairro":"JARDIM FLORESTA"},{"nu_telefone":"(95) 3627-7973"},{"co_cep":"69301970"},{"uf":"RR"},{"cidade":"Boa Vista"},{"ano_ubs_det":"2016"},{"mes_ubs_det":"5"}],"geometry":{"type":"Point","coordinates":[-60.701158046721,2.8340649604797]}},{"type":"Feature","properties":[{"gid":"7763"},{"co_cnes":"2320053"},{"lat":"3.35028861911031"},{"long":"-59.8780066289099"},{"no_fantasia":"CENTRO DE SAUDE CRISTINO JOSE DA SILVA"},{"no_logradouro":"RUA JOAO LOPES DE MAGALHAES"},{"nu_endereco":"S/N"},{"no_bairro":"CENTRO"},{"nu_telefone":""},{"co_cep":"69380000"},{"uf":"RR"},{"cidade":"Bonfim"},{"ano_ubs_det":"2016"},{"mes_ubs_det":"5"}],"geometry":{"type":"Point","coordinates":[-59.87800662891,3.3502886191103]}},{"type":"Feature","properties":[{"gid":"8166"},{"co_cnes":"2589834"},{"lat":"0.87627768516538"},{"long":"-59.6972823142988"},{"no_fantasia":"CENTRO DE SAUDE CLAITON O DA SILVA"},{"no_logradouro":"RUA AMAZONAS"},{"nu_endereco":"S/N"},{"no_bairro":"CENTRO"},{"nu_telefone":""},{"co_cep":"69378000"},{"uf":"RR"},{"cidade":"Caroebe"},{"ano_ubs_det":"2016"},{"mes_ubs_det":"5"}],"geometry":{"type":"Point","coordinates":[-59.697282314299,0.87627768516538]}},{"type":"Feature","properties":[{"gid":"9200"},{"co_cnes":"7024282"},{"lat":"3.65493596515325"},{"long":"-61.3447380065918"},{"no_fantasia":"UNIDADE BASICA DE VILA BRASIL"},{"no_logradouro":"RUA RAUL LIMA"},{"nu_endereco":"S/N"},{"no_bairro":"CENTRO"},{"nu_telefone":""},{"co_cep":"69343000"},{"uf":"RR"},{"cidade":"Amajari"},{"ano_ubs_det":"2016"},{"mes_ubs_det":"5"}],"geometry":{"type":"Point","coordinates":[-61.344738006592,3.6549359651532]}},{"type":"Feature","properties":[{"gid":"9332"},{"co_cnes":"2744449"},{"lat":"2.79781222343437"},{"long":"-60.6830048561079"},{"no_fantasia":"UNIDADE BASICA DE SAUDE 13 DE SETEMBRO"},{"no_logradouro":"AV ELDORADO"},{"nu_endereco":"19"},{"no_bairro":"13 DE SETEMBRO"},{"nu_telefone":"(95)3623 1776"},{"co_cep":"69308000"},{"uf":"RR"},{"cidade":"Boa Vista"},{"ano_ubs_det":"2016"},{"mes_ubs_det":"5"}],"geometry":{"type":"Point","coordinates":[-60.683004856108,2.7978122234344]}},{"type":"Feature","properties":[{"gid":"10020"},{"co_cnes":"2744511"},{"lat":"2.8238352"},{"long":"-60.7170059"},{"no_fantasia":"UNIDADE BASICA DE SAUDE OLENKA MACELLARO THOME VIEIRA"},{"no_logradouro":"AV MARIO HOMEM DE MELO"},{"nu_endereco":"5075"},{"no_bairro":"CAIMBE"},{"nu_telefone":"(95)36268689"},{"co_cep":"69312155"},{"uf":"RR"},{"cidade":"Boa Vista"},{"ano_ubs_det":"2016"},{"mes_ubs_det":"5"}],"geometry":{"type":"Point","coordinates":[-60.7170059,2.8238352]}},{"type":"Feature","properties":[{"gid":"10759"},{"co_cnes":"6890784"},{"lat":"4.431"},{"long":"-61.146"},{"no_fantasia":"POSTO DE SAUDE DO SUAPI"},{"no_logradouro":"RUA ANEL VIARIO"},{"nu_endereco":"S/N"},{"no_bairro":"SUAPI"},{"nu_telefone":""},{"co_cep":"69345000"},{"uf":"RR"},{"cidade":"Pacaraima"},{"ano_ubs_det":"2016"},{"mes_ubs_det":"5"}],"geometry":{"type":"Point","coordinates":[-61.146,4.431]}},{"type":"Feature","properties":[{"gid":"10671"},{"co_cnes":"6886795"},{"lat":"2.47977223505342"},{"long":"-60.9115185306216"},{"no_fantasia":"POSTO DE SAUDE SAGRADA FAMILIA"},{"no_logradouro":"SEBASTIAO CRUZ"},{"nu_endereco":"S/N"},{"no_bairro":"SAGRADA FAMILIA"},{"nu_telefone":""},{"co_cep":"69340000"},{"uf":"RR"},{"cidade":"Mucajaí"},{"ano_ubs_det":"2016"},{"mes_ubs_det":"5"}],"geometry":{"type":"Point","coordinates":[-60.911518530622,2.4797722350534]}},{"type":"Feature","properties":[{"gid":"47940"},{"co_cnes":"6235476"},{"lat":"2.81953"},{"long":"-60.6714"},{"no_fantasia":"SAUDE ITINERANTE"},{"no_logradouro":"RUA MADRI"},{"nu_endereco":"180"},{"no_bairro":"AEROPORTO"},{"nu_telefone":""},{"co_cep":"69310043"},{"uf":"RR"},{"cidade":"Boa Vista"},{"ano_ubs_det":"2016"},{"mes_ubs_det":"5"}],"geometry":{"type":"Point","coordinates":[-60.6714,2.81953]}},{"type":"Feature","properties":[{"gid":"10829"},{"co_cnes":"2319683"},{"lat":"3.6521184454459"},{"long":"-61.420590172663"},{"no_fantasia":"POSTO DE SAUDE TRAIRAO I"},{"no_logradouro":"RUA AFONSO PENA"},{"nu_endereco":"S/N"},{"no_bairro":"ZONA RURAL"},{"nu_telefone":""},{"co_cep":"69343000"},{"uf":"RR"},{"cidade":"Amajari"},{"ano_ubs_det":"2016"},{"mes_ubs_det":"5"}],"geometry":{"type":"Point","coordinates":[-61.420590172663,3.6521184454459]}},{"type":"Feature","properties":[{"gid":"11048"},{"co_cnes":"2320827"},{"lat":"0.583519935607893"},{"long":"-60.4601883888227"},{"no_fantasia":"UNIDADE BASICA DE SAUDE MARIA RAIMUNDA BATISTA"},{"no_logradouro":"AV DOS PALMARES"},{"nu_endereco":"S/N"},{"no_bairro":"CENTRO"},{"nu_telefone":"9532381926"},{"co_cep":"69373000"},{"uf":"RR"},{"cidade":"Rorainópolis"},{"ano_ubs_det":"2016"},{"mes_ubs_det":"5"}],"geometry":{"type":"Point","coordinates":[-60.460188388823,0.58351993560789]}},{"type":"Feature","properties":[{"gid":"11228"},{"co_cnes":"2744554"},{"lat":"2.82535314559928"},{"long":"-60.6625986099226"},{"no_fantasia":"UNIDADE BASICA DE SAUDE IONE SANTIAGO"},{"no_logradouro":"RUA PRESIDENTE COSTA E SILVA"},{"nu_endereco":"356"},{"no_bairro":"SAO PEDRO"},{"nu_telefone":"(95)3623 2200"},{"co_cep":"69301970"},{"uf":"RR"},{"cidade":"Boa Vista"},{"ano_ubs_det":"2016"},{"mes_ubs_det":"5"}],"geometry":{"type":"Point","coordinates":[-60.662598609923,2.8253531455993]}},{"type":"Feature","properties":[{"gid":"11732"},{"co_cnes":"2320835"},{"lat":"0.131943225860592"},{"long":"-60.5695366859418"},{"no_fantasia":"UNIDADE BASICA DE SAUDE VILA DO EQUADOR"},{"no_logradouro":"VILA DO EQUADOR"},{"nu_endereco":"S/N"},{"no_bairro":"CENTRO"},{"nu_telefone":"(95)32381926"},{"co_cep":"69373000"},{"uf":"RR"},{"cidade":"Rorainópolis"},{"ano_ubs_det":"2016"},{"mes_ubs_det":"5"}],"geometry":{"type":"Point","coordinates":[-60.569536685942,0.13194322586059]}},{"type":"Feature","properties":[{"gid":"11959"},{"co_cnes":"7317972"},{"lat":"2.98690000552962"},{"long":"-61.3052179260254"},{"no_fantasia":"CENTRO DE SAUDE JOAO MARIANO"},{"no_logradouro":"AVENIDA GETULIO VARGAS"},{"nu_endereco":"S/N"},{"no_bairro":"MUTIRAO"},{"nu_telefone":""},{"co_cep":"69350000"},{"uf":"RR"},{"cidade":"Alto Alegre"},{"ano_ubs_det":"2016"},{"mes_ubs_det":"5"}],"geometry":{"type":"Point","coordinates":[-61.305217926025,2.9869000055296]}},{"type":"Feature","properties":[{"gid":"12163"},{"co_cnes":"2476738"},{"lat":"0.800993442535377"},{"long":"-59.4273662567121"},{"no_fantasia":"CENTRO DE SAUDE WALTER GOMES PORTELA"},{"no_logradouro":"VILA DE ENTRE RIOS"},{"nu_endereco":"S/N"},{"no_bairro":"DISTRITO"},{"nu_telefone":"95988017475"},{"co_cep":"69378000"},{"uf":"RR"},{"cidade":"Caroebe"},{"ano_ubs_det":"2016"},{"mes_ubs_det":"5"}],"geometry":{"type":"Point","coordinates":[-59.427366256712,0.80099344253538]}},{"type":"Feature","properties":[{"gid":"12726"},{"co_cnes":"2476770"},{"lat":"2.57973790168755"},{"long":"-60.9690141677839"},{"no_fantasia":"POSTO DE SAUDE FRIDA SCHILLREFF"},{"no_logradouro":"VILA DO TAMANDARE"},{"nu_endereco":"S/N"},{"no_bairro":"CENTRO"},{"nu_telefone":""},{"co_cep":"69340000"},{"uf":"RR"},{"cidade":"Mucajaí"},{"ano_ubs_det":"2016"},{"mes_ubs_det":"5"}],"geometry":{"type":"Point","coordinates":[-60.969014167784,2.5797379016876]}},{"type":"Feature","properties":[{"gid":"12712"},{"co_cnes":"2319969"},{"lat":"2.99382294765484"},{"long":"-61.3140223901178"},{"no_fantasia":"CENTRO DE SAUDE ANA PEREIRA"},{"no_logradouro":"RUA JOAO 23"},{"nu_endereco":"S/N"},{"no_bairro":"CENTRO"},{"nu_telefone":""},{"co_cep":"69350000"},{"uf":"RR"},{"cidade":"Alto Alegre"},{"ano_ubs_det":"2016"},{"mes_ubs_det":"5"}],"geometry":{"type":"Point","coordinates":[-61.314022390118,2.9938229476548]}},{"type":"Feature","properties":[{"gid":"12847"},{"co_cnes":"2657198"},{"lat":"3.07183742523184"},{"long":"-61.6016721725446"},{"no_fantasia":"POSTO DE SAUDE PAREDAO NOVO"},{"no_logradouro":"VILA PAREDAO"},{"nu_endereco":"S/N"},{"no_bairro":"CENTRO"},{"nu_telefone":""},{"co_cep":"69350000"},{"uf":"RR"},{"cidade":"Alto Alegre"},{"ano_ubs_det":"2016"},{"mes_ubs_det":"5"}],"geometry":{"type":"Point","coordinates":[-61.601672172545,3.0718374252318]}},{"type":"Feature","properties":[{"gid":"13560"},{"co_cnes":"2320363"},{"lat":"2.11191773414606"},{"long":"-60.6170225143415"},{"no_fantasia":"POSTO DE SAUDE FELIX PINTO"},{"no_logradouro":"RUA PRINCIPAL"},{"nu_endereco":"S/N"},{"no_bairro":"CENTRO"},{"nu_telefone":"(95) 991726608"},{"co_cep":"69390000"},{"uf":"RR"},{"cidade":"Cantá"},{"ano_ubs_det":"2016"},{"mes_ubs_det":"5"}],"geometry":{"type":"Point","coordinates":[-60.617022514341,2.1119177341461]}},{"type":"Feature","properties":[{"gid":"13865"},{"co_cnes":"2550261"},{"lat":"2.8253002"},{"long":"-60.6713929"},{"no_fantasia":"UNIDADE BASICA DE SAUDE DR HELIO MACEDO"},{"no_logradouro":"RUA JOCA FARIAS"},{"nu_endereco":"2199"},{"no_bairro":"JARDIM CARANA"},{"nu_telefone":"(95) 36259550"},{"co_cep":"69313600"},{"uf":"RR"},{"cidade":"Boa Vista"},{"ano_ubs_det":"2016"},{"mes_ubs_det":"5"}],"geometry":{"type":"Point","coordinates":[-60.6713929,2.8253002]}},{"type":"Feature","properties":[{"gid":"13971"},{"co_cnes":"2319667"},{"lat":"3.6531"},{"long":"-61.3714642"},{"no_fantasia":"CENTRO DE SAUDE JAIR DA SILVA MOTA"},{"no_logradouro":"RUA JOSE PEREIRA DA SILVA"},{"nu_endereco":"S/N"},{"no_bairro":"CENTRO"},{"nu_telefone":"(95)3593 1087"},{"co_cep":"69343000"},{"uf":"RR"},{"cidade":"Amajari"},{"ano_ubs_det":"2016"},{"mes_ubs_det":"5"}],"geometry":{"type":"Point","coordinates":[-61.3714642,3.6531]}},{"type":"Feature","properties":[{"gid":"13817"},{"co_cnes":"2476746"},{"lat":"0.937195393597556"},{"long":"-60.4250604939819"},{"no_fantasia":"UNIDADE BASICA DE SAUDE ANTONIO CARLOS PEREIRA"},{"no_logradouro":"AV 7 DE SETEMBRO"},{"nu_endereco":"S/N"},{"no_bairro":"CENTRO"},{"nu_telefone":"(95)2381926"},{"co_cep":"69373000"},{"uf":"RR"},{"cidade":"Rorainópolis"},{"ano_ubs_det":"2016"},{"mes_ubs_det":"5"}],"geometry":{"type":"Point","coordinates":[-60.425060493982,0.93719539359756]}},{"type":"Feature","properties":[{"gid":"13893"},{"co_cnes":"5446627"},{"lat":"2.81668191910439"},{"long":"-60.670532672965"},{"no_fantasia":"UNIDADE BASICA DE SAUDE LUPERCIO LIMA FERREIRA"},{"no_logradouro":"RUA NAZARE FIGUEIRA C LAURA PINHEIRO MAIA"},{"nu_endereco":"S/N"},{"no_bairro":"PINTOLANDIA"},{"nu_telefone":"(95) 3625-4564"},{"co_cep":"69301970"},{"uf":"RR"},{"cidade":"Boa Vista"},{"ano_ubs_det":"2016"},{"mes_ubs_det":"5"}],"geometry":{"type":"Point","coordinates":[-60.670532672965,2.8166819191044]}},{"type":"Feature","properties":[{"gid":"13870"},{"co_cnes":"2566605"},{"lat":"2.79294133186332"},{"long":"-60.7416272163373"},{"no_fantasia":"UNIDADE BASICA DE SAUDE SENADOR HELIO CAMPOS"},{"no_logradouro":"RUA PEDRO ALDEMAR BANTI"},{"nu_endereco":"28"},{"no_bairro":"SENADOR HELIO CAMPOS"},{"nu_telefone":"(95) 3621-6056"},{"co_cep":"69301970"},{"uf":"RR"},{"cidade":"Boa Vista"},{"ano_ubs_det":"2016"},{"mes_ubs_det":"5"}],"geometry":{"type":"Point","coordinates":[-60.741627216337,2.7929413318633]}},{"type":"Feature","properties":[{"gid":"14353"},{"co_cnes":"2319985"},{"lat":"4.19406294822681"},{"long":"-60.7914948463422"},{"no_fantasia":"POSTO DE SAUDE SURUMU"},{"no_logradouro":"AV NOSSA SENHORA DO PERPETUO SOCORRO"},{"nu_endereco":"S/N"},{"no_bairro":"CENTRO"},{"nu_telefone":""},{"co_cep":"69345000"},{"uf":"RR"},{"cidade":"Pacaraima"},{"ano_ubs_det":"2016"},{"mes_ubs_det":"5"}],"geometry":{"type":"Point","coordinates":[-60.791494846342,4.1940629482268]}},{"type":"Feature","properties":[{"gid":"14180"},{"co_cnes":"2817764"},{"lat":"0.88642398718925"},{"long":"-60.3875541687012"},{"no_fantasia":"UNIDADE BASICA DE SAUDE MANOEL LUIZ RODRIGUES"},{"no_logradouro":"RUA PROJETADA"},{"nu_endereco":"S/N"},{"no_bairro":"BRIGADEIRO SANTA MAR"},{"nu_telefone":"(95)32381926"},{"co_cep":"69373000"},{"uf":"RR"},{"cidade":"Rorainópolis"},{"ano_ubs_det":"2016"},{"mes_ubs_det":"5"}],"geometry":{"type":"Point","coordinates":[-60.387554168701,0.88642398718925]}},{"type":"Feature","properties":[{"gid":"14071"},{"co_cnes":"5877946"},{"lat":"4.596"},{"long":"-60.168"},{"no_fantasia":"UNIDADE SAUDE DA FAMILIA UIRAMUTA JOSE JULIO"},{"no_logradouro":"RUA MUTUM"},{"nu_endereco":"S/N"},{"no_bairro":"CENTRO"},{"nu_telefone":""},{"co_cep":"69358000"},{"uf":"RR"},{"cidade":"Uiramutã"},{"ano_ubs_det":"2016"},{"mes_ubs_det":"5"}],"geometry":{"type":"Point","coordinates":[-60.168,4.596]}},{"type":"Feature","properties":[{"gid":"14450"},{"co_cnes":"2744481"},{"lat":"2.76065826416008"},{"long":"-60.7287311553937"},{"no_fantasia":"UNIDADE BASICA DE SAUDE DELIO TUPINAMBA"},{"no_logradouro":"AVENIDA BELO HORIZONTE"},{"nu_endereco":"178"},{"no_bairro":"NOVA CIDADE"},{"nu_telefone":"(95)36267138"},{"co_cep":"69301970"},{"uf":"RR"},{"cidade":"Boa Vista"},{"ano_ubs_det":"2016"},{"mes_ubs_det":"5"}],"geometry":{"type":"Point","coordinates":[-60.728731155394,2.7606582641601]}},{"type":"Feature","properties":[{"gid":"14530"},{"co_cnes":"2566478"},{"lat":"2.82369017601005"},{"long":"-60.7343101501447"},{"no_fantasia":"UNIDADE BASICA DE SAUDE TANCREDO NEVES"},{"no_logradouro":"AV SAO SEBASTIAO COM RUT PINHEIRO"},{"nu_endereco":"S/N"},{"no_bairro":"JARDIM TANCREDO NEVE"},{"nu_telefone":"(95) 36287121"},{"co_cep":"69301970"},{"uf":"RR"},{"cidade":"Boa Vista"},{"ano_ubs_det":"2016"},{"mes_ubs_det":"5"}],"geometry":{"type":"Point","coordinates":[-60.734310150145,2.8236901760101]}},{"type":"Feature","properties":[{"gid":"14767"},{"co_cnes":"2744538"},{"lat":"2.81668191910439"},{"long":"-60.670532672965"},{"no_fantasia":"UNIDADE BASICA DE SAUDE PRICUMA"},{"no_logradouro":"AV VIA DAS FLORES"},{"nu_endereco":"2347"},{"no_bairro":"PRICUMA"},{"nu_telefone":"(95)3625 1007"},{"co_cep":"69301970"},{"uf":"RR"},{"cidade":"Boa Vista"},{"ano_ubs_det":"2016"},{"mes_ubs_det":"5"}],"geometry":{"type":"Point","coordinates":[-60.670532672965,2.8166819191044]}},{"type":"Feature","properties":[{"gid":"15258"},{"co_cnes":"6571999"},{"lat":"2.84884929656974"},{"long":"-60.7480001449567"},{"no_fantasia":"UNIDADE BASICA DE SAUDE AYGARA MOTTA PEREIRA"},{"no_logradouro":"RUA J"},{"nu_endereco":"256"},{"no_bairro":"CIDADE SATELITE"},{"nu_telefone":"36286943"},{"co_cep":"69301970"},{"uf":"RR"},{"cidade":"Boa Vista"},{"ano_ubs_det":"2016"},{"mes_ubs_det":"5"}],"geometry":{"type":"Point","coordinates":[-60.748000144957,2.8488492965697]}},{"type":"Feature","properties":[{"gid":"16049"},{"co_cnes":"2320843"},{"lat":"2.30544447898858"},{"long":"-61.251976490019"},{"no_fantasia":"POSTO DE SAUDE ZENIR MATOS DE ALMEIDA"},{"no_logradouro":"VILA DO ROXINHO"},{"nu_endereco":"S/N"},{"no_bairro":"CENTRO"},{"nu_telefone":""},{"co_cep":"69340000"},{"uf":"RR"},{"cidade":"Mucajaí"},{"ano_ubs_det":"2016"},{"mes_ubs_det":"5"}],"geometry":{"type":"Point","coordinates":[-61.251976490019,2.3054444789886]}},{"type":"Feature","properties":[{"gid":"16851"},{"co_cnes":"5446627"},{"lat":"2.81668191910439"},{"long":"-60.670532672965"},{"no_fantasia":"UNIDADE BASICA DE SAUDE LUPERCIO LIMA FERREIRA"},{"no_logradouro":"RUA NAZARE FIGUEIRA C LAURA PINHEIRO MAIA"},{"nu_endereco":"S/N"},{"no_bairro":"PINTOLANDIA"},{"nu_telefone":"(95) 3625-4564"},{"co_cep":"69301970"},{"uf":"RR"},{"cidade":"Boa Vista"},{"ano_ubs_det":"2016"},{"mes_ubs_det":"5"}],"geometry":{"type":"Point","coordinates":[-60.670532672965,2.8166819191044]}},{"type":"Feature","properties":[{"gid":"16919"},{"co_cnes":"2320819"},{"lat":"0.946"},{"long":"-60.418"},{"no_fantasia":"UNIDADE BASICA DE SAUDE ANTONIO LUCAS DE SOUZA"},{"no_logradouro":"VILA JUNDIA"},{"nu_endereco":"S/N"},{"no_bairro":"CENTRO"},{"nu_telefone":"( 95)32381247"},{"co_cep":"69373000"},{"uf":"RR"},{"cidade":"Rorainópolis"},{"ano_ubs_det":"2016"},{"mes_ubs_det":"5"}],"geometry":{"type":"Point","coordinates":[-60.418,0.946]}},{"type":"Feature","properties":[{"gid":"17858"},{"co_cnes":"2566591"},{"lat":"2.80018329620353"},{"long":"-60.7592439651472"},{"no_fantasia":"UNIDADE BASICA DE SAUDE SAYONARA MARIA DANTAS LICARIAO MATOS"},{"no_logradouro":"AVENIDA RAIMUNDO RODRIGUES COELHO"},{"nu_endereco":"2280"},{"no_bairro":"SENADOR HELIO CAMPOS"},{"nu_telefone":"(95) 32248452"},{"co_cep":"69316392"},{"uf":"RR"},{"cidade":"Boa Vista"},{"ano_ubs_det":"2016"},{"mes_ubs_det":"5"}],"geometry":{"type":"Point","coordinates":[-60.759243965147,2.8001832962035]}},{"type":"Feature","properties":[{"gid":"17792"},{"co_cnes":"2320746"},{"lat":"1.73594713211055"},{"long":"-61.1425852775556"},{"no_fantasia":"CENTRO DE SAUDE DE VISTA ALEGRE"},{"no_logradouro":"BR174"},{"nu_endereco":"S/N"},{"no_bairro":"VILA VISTA ALEGRE"},{"nu_telefone":"(95)5321427"},{"co_cep":"69360000"},{"uf":"RR"},{"cidade":"Caracaraí"},{"ano_ubs_det":"2016"},{"mes_ubs_det":"5"}],"geometry":{"type":"Point","coordinates":[-61.142585277556,1.7359471321105]}},{"type":"Feature","properties":[{"gid":"18508"},{"co_cnes":"2320568"},{"lat":"4.47525934021225"},{"long":"-61.1473063471493"},{"no_fantasia":"UNIDADE DE REFERENCIA DE SAUDE DA FAMILIA"},{"no_logradouro":"MONTE RORAIMA"},{"nu_endereco":"S/N"},{"no_bairro":"VILA NOVA"},{"nu_telefone":""},{"co_cep":"69345000"},{"uf":"RR"},{"cidade":"Pacaraima"},{"ano_ubs_det":"2016"},{"mes_ubs_det":"5"}],"geometry":{"type":"Point","coordinates":[-61.147306347149,4.4752593402122]}},{"type":"Feature","properties":[{"gid":"19109"},{"co_cnes":"2744473"},{"lat":"2.8281905"},{"long":"-60.6688629"},{"no_fantasia":"UNIDADE BASICA DE SAUDE BURITIS"},{"no_logradouro":"RUA RAIMUNDO FIGUEIRAS"},{"nu_endereco":"661"},{"no_bairro":"BURITIS"},{"nu_telefone":"(95)3625 7454"},{"co_cep":"69309182"},{"uf":"RR"},{"cidade":"Boa Vista"},{"ano_ubs_det":"2016"},{"mes_ubs_det":"5"}],"geometry":{"type":"Point","coordinates":[-60.6688629,2.8281905]}},{"type":"Feature","properties":[{"gid":"19468"},{"co_cnes":"2744570"},{"lat":"2.81668191910439"},{"long":"-60.670532672965"},{"no_fantasia":"UNIDADE BASICA DE SAUDE DR SILVIO LOFEGO BOTELHO"},{"no_logradouro":"AV MINAS GERAIS"},{"nu_endereco":"512"},{"no_bairro":"DOS ESTADOS"},{"nu_telefone":"(95)36238714"},{"co_cep":"69301000"},{"uf":"RR"},{"cidade":"Boa Vista"},{"ano_ubs_det":"2016"},{"mes_ubs_det":"5"}],"geometry":{"type":"Point","coordinates":[-60.670532672965,2.8166819191044]}},{"type":"Feature","properties":[{"gid":"19359"},{"co_cnes":"2320746"},{"lat":"1.73594713211055"},{"long":"-61.1425852775556"},{"no_fantasia":"CENTRO DE SAUDE DE VISTA ALEGRE"},{"no_logradouro":"BR174"},{"nu_endereco":"S/N"},{"no_bairro":"VILA VISTA ALEGRE"},{"nu_telefone":"(95)5321427"},{"co_cep":"69360000"},{"uf":"RR"},{"cidade":"Caracaraí"},{"ano_ubs_det":"2016"},{"mes_ubs_det":"5"}],"geometry":{"type":"Point","coordinates":[-61.142585277556,1.7359471321105]}},{"type":"Feature","properties":[{"gid":"19463"},{"co_cnes":"2566753"},{"lat":"2.81668191910439"},{"long":"-60.670532672965"},{"no_fantasia":"UNIDADE BASICA DE SAUDE CARANA"},{"no_logradouro":"RUA VALMIR PEREIRA DA ROCHA"},{"nu_endereco":"98"},{"no_bairro":"CARANA"},{"nu_telefone":"(95) 36267499"},{"co_cep":"69313620"},{"uf":"RR"},{"cidade":"Boa Vista"},{"ano_ubs_det":"2016"},{"mes_ubs_det":"5"}],"geometry":{"type":"Point","coordinates":[-60.670532672965,2.8166819191044]}},{"type":"Feature","properties":[{"gid":"19470"},{"co_cnes":"3068927"},{"lat":"3.37697625160207"},{"long":"-59.8160290718061"},{"no_fantasia":"UBS DIMINIZ DINIZ DA SILVA"},{"no_logradouro":"RUA SAO FRANCISCO"},{"nu_endereco":"S/N"},{"no_bairro":"SAO FRANCISCO"},{"nu_telefone":""},{"co_cep":"69380000"},{"uf":"RR"},{"cidade":"Bonfim"},{"ano_ubs_det":"2016"},{"mes_ubs_det":"5"}],"geometry":{"type":"Point","coordinates":[-59.816029071806,3.3769762516021]}},{"type":"Feature","properties":[{"gid":"19472"},{"co_cnes":"2320207"},{"lat":"2.61"},{"long":"-60.597"},{"no_fantasia":"CENTRO DE SAUDE SEBASTIAO RODRIGUES SILVA"},{"no_logradouro":"RENATO COSTA DE ALMEIDA"},{"nu_endereco":"100"},{"no_bairro":"CENTRO"},{"nu_telefone":"(95)991647124"},{"co_cep":"69390000"},{"uf":"RR"},{"cidade":"Cantá"},{"ano_ubs_det":"2016"},{"mes_ubs_det":"5"}],"geometry":{"type":"Point","coordinates":[-60.597,2.61]}},{"type":"Feature","properties":[{"gid":"19469"},{"co_cnes":"2744546"},{"lat":"2.8363072872161"},{"long":"-60.7149767875654"},{"no_fantasia":"UNIDADE BASICA DE SAUDE PROF MARIANO DE ANDRADE"},{"no_logradouro":"AVENIDA DECO FONTELIS"},{"nu_endereco":"264"},{"no_bairro":"CARANA"},{"nu_telefone":"(95)3627 1327"},{"co_cep":"69301970"},{"uf":"RR"},{"cidade":"Boa Vista"},{"ano_ubs_det":"2016"},{"mes_ubs_det":"5"}],"geometry":{"type":"Point","coordinates":[-60.714976787565,2.8363072872161]}},{"type":"Feature","properties":[{"gid":"19464"},{"co_cnes":"6006396"},{"lat":"2.81668191910439"},{"long":"-60.670532672965"},{"no_fantasia":"UNIDADE BASICA DE SAUDE PASTOR LUCIANO GALDINO RABELO"},{"no_logradouro":"RUA BRESCIA C BOLONIA"},{"nu_endereco":"S/N"},{"no_bairro":"CENTENARIO"},{"nu_telefone":"95-36232652"},{"co_cep":"69301970"},{"uf":"RR"},{"cidade":"Boa Vista"},{"ano_ubs_det":"2016"},{"mes_ubs_det":"5"}],"geometry":{"type":"Point","coordinates":[-60.670532672965,2.8166819191044]}},{"type":"Feature","properties":[{"gid":"19465"},{"co_cnes":"2744457"},{"lat":"2.81668191910439"},{"long":"-60.670532672965"},{"no_fantasia":"UNIDADE BASICA DE SAUDE 31 DE MARCO"},{"no_logradouro":"RUA MAJOR CARLOS MARDEL"},{"nu_endereco":"466"},{"no_bairro":"31 DE MARCO"},{"nu_telefone":"(95)3623 - 1822"},{"co_cep":"69301970"},{"uf":"RR"},{"cidade":"Boa Vista"},{"ano_ubs_det":"2016"},{"mes_ubs_det":"5"}],"geometry":{"type":"Point","coordinates":[-60.670532672965,2.8166819191044]}},{"type":"Feature","properties":[{"gid":"19274"},{"co_cnes":"2744562"},{"lat":"2.81668191910439"},{"long":"-60.670532672965"},{"no_fantasia":"UNIDADE BASICA DE SAUDE SAO VICENTE"},{"no_logradouro":"AV PRESIDENTE CASTELO BRANCO"},{"nu_endereco":"1875"},{"no_bairro":"SAO VICENTE"},{"nu_telefone":"(95)3623 1556"},{"co_cep":"69301000"},{"uf":"RR"},{"cidade":"Boa Vista"},{"ano_ubs_det":"2016"},{"mes_ubs_det":"5"}],"geometry":{"type":"Point","coordinates":[-60.670532672965,2.8166819191044]}},{"type":"Feature","properties":[{"gid":"19833"},{"co_cnes":"2320789"},{"lat":"1.005"},{"long":"-60.159"},{"no_fantasia":"CENTRO DE SAUDE REGINA RIBEIRO PAIVA"},{"no_logradouro":"AVENIDA JOAO RODRIGUES DA SILVA"},{"nu_endereco":"S/N"},{"no_bairro":"CENTRO"},{"nu_telefone":"95-35371021"},{"co_cep":"69370000"},{"uf":"RR"},{"cidade":"São Luiz"},{"ano_ubs_det":"2016"},{"mes_ubs_det":"5"}],"geometry":{"type":"Point","coordinates":[-60.159,1.005]}},{"type":"Feature","properties":[{"gid":"20137"},{"co_cnes":"2589966"},{"lat":"3.35028861911031"},{"long":"-59.8780066289099"},{"no_fantasia":"UBS VILENA"},{"no_logradouro":"AV BRASIL"},{"nu_endereco":"S/N"},{"no_bairro":"VILA VILENA"},{"nu_telefone":""},{"co_cep":"69380000"},{"uf":"RR"},{"cidade":"Bonfim"},{"ano_ubs_det":"2016"},{"mes_ubs_det":"5"}],"geometry":{"type":"Point","coordinates":[-59.87800662891,3.3502886191103]}},{"type":"Feature","properties":[{"gid":"20003"},{"co_cnes":"2657279"},{"lat":"-1.17461442947384"},{"long":"-61.9046330451947"},{"no_fantasia":"CENTRO DE SAUDE AMAJAU CACHOEIRINHA"},{"no_logradouro":"VILA CACHOEIRINHA"},{"nu_endereco":"S/N"},{"no_bairro":"BAIXO RIO BRANCO"},{"nu_telefone":""},{"co_cep":"69360000"},{"uf":"RR"},{"cidade":"Caracaraí"},{"ano_ubs_det":"2016"},{"mes_ubs_det":"5"}],"geometry":{"type":"Point","coordinates":[-61.904633045195,-1.1746144294738]}},{"type":"Feature","properties":[{"gid":"20352"},{"co_cnes":"2476762"},{"lat":"2.58968353271477"},{"long":"-61.460180282591"},{"no_fantasia":"POSTO DE SAUDE FRANCISCO ALVES LIMA"},{"no_logradouro":"VILA DA PENHA"},{"nu_endereco":"S/N"},{"no_bairro":"CENTRO"},{"nu_telefone":""},{"co_cep":"69340000"},{"uf":"RR"},{"cidade":"Mucajaí"},{"ano_ubs_det":"2016"},{"mes_ubs_det":"5"}],"geometry":{"type":"Point","coordinates":[-61.460180282591,2.5896835327148]}},{"type":"Feature","properties":[{"gid":"21030"},{"co_cnes":"2566648"},{"lat":"2.81668191910439"},{"long":"-60.670532672965"},{"no_fantasia":"UNIDADE BASICA DE SAUDE CINTURAO VERDE"},{"no_logradouro":"RUA SANTA CLARA"},{"nu_endereco":"1081"},{"no_bairro":"CINTURAO VERDE"},{"nu_telefone":"(95)36232652"},{"co_cep":"69301970"},{"uf":"RR"},{"cidade":"Boa Vista"},{"ano_ubs_det":"2016"},{"mes_ubs_det":"5"}],"geometry":{"type":"Point","coordinates":[-60.670532672965,2.8166819191044]}},{"type":"Feature","properties":[{"gid":"25678"},{"co_cnes":"2320290"},{"lat":"2.61"},{"long":"-60.597"},{"no_fantasia":"POSTO DE SAUDE SERRA GRANDE II"},{"no_logradouro":"RUA PRINCIPAL"},{"nu_endereco":"S/N"},{"no_bairro":"CENTRO"},{"nu_telefone":"(95) 991376576"},{"co_cep":"69390000"},{"uf":"RR"},{"cidade":"Cantá"},{"ano_ubs_det":"2016"},{"mes_ubs_det":"5"}],"geometry":{"type":"Point","coordinates":[-60.597,2.61]}},{"type":"Feature","properties":[{"gid":"26068"},{"co_cnes":"7271603"},{"lat":"2.61"},{"long":"-60.597"},{"no_fantasia":"CENTRO DE SAUDE JOSE EUCIO RODRIGUES"},{"no_logradouro":"RUA VINICIUS DE MORAES"},{"nu_endereco":"122"},{"no_bairro":"SANTA CECILIA"},{"nu_telefone":"991158138"},{"co_cep":"69390000"},{"uf":"RR"},{"cidade":"Cantá"},{"ano_ubs_det":"2016"},{"mes_ubs_det":"5"}],"geometry":{"type":"Point","coordinates":[-60.597,2.61]}},{"type":"Feature","properties":[{"gid":"26188"},{"co_cnes":"2320770"},{"lat":"0.940779447555515"},{"long":"-59.9126315116865"},{"no_fantasia":"CENTRO DE SAUDE DE SAO JOAO DA BALIZA"},{"no_logradouro":"AV SAO PAULO"},{"nu_endereco":"S/N"},{"no_bairro":"NOVA ESPERANCA"},{"nu_telefone":"(95)2351616"},{"co_cep":"69375000"},{"uf":"RR"},{"cidade":"São João da Baliza"},{"ano_ubs_det":"2016"},{"mes_ubs_det":"5"}],"geometry":{"type":"Point","coordinates":[-59.912631511686,0.94077944755552]}},{"type":"Feature","properties":[{"gid":"26139"},{"co_cnes":"2657392"},{"lat":"1.67740696795137"},{"long":"-61.0873746871948"},{"no_fantasia":"CENTRO DE SAUDE PETROLINA DO NORTE"},{"no_logradouro":"VILA PETROLINA"},{"nu_endereco":"S/N"},{"no_bairro":"INTERIOR"},{"nu_telefone":""},{"co_cep":"69360000"},{"uf":"RR"},{"cidade":"Caracaraí"},{"ano_ubs_det":"2016"},{"mes_ubs_det":"5"}],"geometry":{"type":"Point","coordinates":[-61.087374687195,1.6774069679514]}},{"type":"Feature","properties":[{"gid":"26165"},{"co_cnes":"2320770"},{"lat":"0.940779447555515"},{"long":"-59.9126315116865"},{"no_fantasia":"CENTRO DE SAUDE DE SAO JOAO DA BALIZA"},{"no_logradouro":"AV SAO PAULO"},{"nu_endereco":"S/N"},{"no_bairro":"NOVA ESPERANCA"},{"nu_telefone":"(95)2351616"},{"co_cep":"69375000"},{"uf":"RR"},{"cidade":"São João da Baliza"},{"ano_ubs_det":"2016"},{"mes_ubs_det":"5"}],"geometry":{"type":"Point","coordinates":[-59.912631511686,0.94077944755552]}},{"type":"Feature","properties":[{"gid":"27326"},{"co_cnes":"2589966"},{"lat":"3.35028861911031"},{"long":"-59.8780066289099"},{"no_fantasia":"UBS VILENA"},{"no_logradouro":"AV BRASIL"},{"nu_endereco":"S/N"},{"no_bairro":"VILA VILENA"},{"nu_telefone":""},{"co_cep":"69380000"},{"uf":"RR"},{"cidade":"Bonfim"},{"ano_ubs_det":"2016"},{"mes_ubs_det":"5"}],"geometry":{"type":"Point","coordinates":[-59.87800662891,3.3502886191103]}},{"type":"Feature","properties":[{"gid":"28133"},{"co_cnes":"2550261"},{"lat":"2.8253002"},{"long":"-60.6713929"},{"no_fantasia":"UNIDADE BASICA DE SAUDE DR HELIO MACEDO"},{"no_logradouro":"RUA JOCA FARIAS"},{"nu_endereco":"2199"},{"no_bairro":"JARDIM CARANA"},{"nu_telefone":"(95) 36259550"},{"co_cep":"69313600"},{"uf":"RR"},{"cidade":"Boa Vista"},{"ano_ubs_det":"2016"},{"mes_ubs_det":"5"}],"geometry":{"type":"Point","coordinates":[-60.6713929,2.8253002]}},{"type":"Feature","properties":[{"gid":"28166"},{"co_cnes":"2319985"},{"lat":"4.19406294822681"},{"long":"-60.7914948463422"},{"no_fantasia":"POSTO DE SAUDE SURUMU"},{"no_logradouro":"AV NOSSA SENHORA DO PERPETUO SOCORRO"},{"nu_endereco":"S/N"},{"no_bairro":"CENTRO"},{"nu_telefone":""},{"co_cep":"69345000"},{"uf":"RR"},{"cidade":"Pacaraima"},{"ano_ubs_det":"2016"},{"mes_ubs_det":"5"}],"geometry":{"type":"Point","coordinates":[-60.791494846342,4.1940629482268]}},{"type":"Feature","properties":[{"gid":"28607"},{"co_cnes":"2320258"},{"lat":"2.61002540588371"},{"long":"-60.5974316596967"},{"no_fantasia":"POSTO DE SAUDE DO CANTA"},{"no_logradouro":"FRANCISCO CUNHA"},{"nu_endereco":"S/N"},{"no_bairro":"CENTRO"},{"nu_telefone":"(95)5531189"},{"co_cep":"69390000"},{"uf":"RR"},{"cidade":"Cantá"},{"ano_ubs_det":"2016"},{"mes_ubs_det":"5"}],"geometry":{"type":"Point","coordinates":[-60.597431659697,2.6100254058837]}},{"type":"Feature","properties":[{"gid":"28543"},{"co_cnes":"2319683"},{"lat":"3.6521184454459"},{"long":"-61.420590172663"},{"no_fantasia":"POSTO DE SAUDE TRAIRAO I"},{"no_logradouro":"RUA AFONSO PENA"},{"nu_endereco":"S/N"},{"no_bairro":"ZONA RURAL"},{"nu_telefone":""},{"co_cep":"69343000"},{"uf":"RR"},{"cidade":"Amajari"},{"ano_ubs_det":"2016"},{"mes_ubs_det":"5"}],"geometry":{"type":"Point","coordinates":[-61.420590172663,3.6521184454459]}},{"type":"Feature","properties":[{"gid":"28529"},{"co_cnes":"2320053"},{"lat":"3.35028861911031"},{"long":"-59.8780066289099"},{"no_fantasia":"CENTRO DE SAUDE CRISTINO JOSE DA SILVA"},{"no_logradouro":"RUA JOAO LOPES DE MAGALHAES"},{"nu_endereco":"S/N"},{"no_bairro":"CENTRO"},{"nu_telefone":""},{"co_cep":"69380000"},{"uf":"RR"},{"cidade":"Bonfim"},{"ano_ubs_det":"2016"},{"mes_ubs_det":"5"}],"geometry":{"type":"Point","coordinates":[-59.87800662891,3.3502886191103]}},{"type":"Feature","properties":[{"gid":"28609"},{"co_cnes":"2320789"},{"lat":"1.005"},{"long":"-60.159"},{"no_fantasia":"CENTRO DE SAUDE REGINA RIBEIRO PAIVA"},{"no_logradouro":"AVENIDA JOAO RODRIGUES DA SILVA"},{"nu_endereco":"S/N"},{"no_bairro":"CENTRO"},{"nu_telefone":"95-35371021"},{"co_cep":"69370000"},{"uf":"RR"},{"cidade":"São Luiz"},{"ano_ubs_det":"2016"},{"mes_ubs_det":"5"}],"geometry":{"type":"Point","coordinates":[-60.159,1.005]}},{"type":"Feature","properties":[{"gid":"29012"},{"co_cnes":"2744481"},{"lat":"2.76065826416008"},{"long":"-60.7287311553937"},{"no_fantasia":"UNIDADE BASICA DE SAUDE DELIO TUPINAMBA"},{"no_logradouro":"AVENIDA BELO HORIZONTE"},{"nu_endereco":"178"},{"no_bairro":"NOVA CIDADE"},{"nu_telefone":"(95)36267138"},{"co_cep":"69301970"},{"uf":"RR"},{"cidade":"Boa Vista"},{"ano_ubs_det":"2016"},{"mes_ubs_det":"5"}],"geometry":{"type":"Point","coordinates":[-60.728731155394,2.7606582641601]}},{"type":"Feature","properties":[{"gid":"29001"},{"co_cnes":"2744457"},{"lat":"2.81668191910439"},{"long":"-60.670532672965"},{"no_fantasia":"UNIDADE BASICA DE SAUDE 31 DE MARCO"},{"no_logradouro":"RUA MAJOR CARLOS MARDEL"},{"nu_endereco":"466"},{"no_bairro":"31 DE MARCO"},{"nu_telefone":"(95)3623 - 1822"},{"co_cep":"69301970"},{"uf":"RR"},{"cidade":"Boa Vista"},{"ano_ubs_det":"2016"},{"mes_ubs_det":"5"}],"geometry":{"type":"Point","coordinates":[-60.670532672965,2.8166819191044]}},{"type":"Feature","properties":[{"gid":"29006"},{"co_cnes":"6006396"},{"lat":"2.81668191910439"},{"long":"-60.670532672965"},{"no_fantasia":"UNIDADE BASICA DE SAUDE PASTOR LUCIANO GALDINO RABELO"},{"no_logradouro":"RUA BRESCIA C BOLONIA"},{"nu_endereco":"S/N"},{"no_bairro":"CENTENARIO"},{"nu_telefone":"95-36232652"},{"co_cep":"69301970"},{"uf":"RR"},{"cidade":"Boa Vista"},{"ano_ubs_det":"2016"},{"mes_ubs_det":"5"}],"geometry":{"type":"Point","coordinates":[-60.670532672965,2.8166819191044]}},{"type":"Feature","properties":[{"gid":"29013"},{"co_cnes":"2566265"},{"lat":"2.83406496047965"},{"long":"-60.7011580467207"},{"no_fantasia":"UNIDADE BASICA DE SAUDE JARDIM FLORESTA"},{"no_logradouro":"RUA ANA CECILIA MOTA DA SILVA"},{"nu_endereco":"S/N"},{"no_bairro":"JARDIM FLORESTA"},{"nu_telefone":"(95) 3627-7973"},{"co_cep":"69301970"},{"uf":"RR"},{"cidade":"Boa Vista"},{"ano_ubs_det":"2016"},{"mes_ubs_det":"5"}],"geometry":{"type":"Point","coordinates":[-60.701158046721,2.8340649604797]}},{"type":"Feature","properties":[{"gid":"29136"},{"co_cnes":"2744570"},{"lat":"2.81668191910439"},{"long":"-60.670532672965"},{"no_fantasia":"UNIDADE BASICA DE SAUDE DR SILVIO LOFEGO BOTELHO"},{"no_logradouro":"AV MINAS GERAIS"},{"nu_endereco":"512"},{"no_bairro":"DOS ESTADOS"},{"nu_telefone":"(95)36238714"},{"co_cep":"69301000"},{"uf":"RR"},{"cidade":"Boa Vista"},{"ano_ubs_det":"2016"},{"mes_ubs_det":"5"}],"geometry":{"type":"Point","coordinates":[-60.670532672965,2.8166819191044]}},{"type":"Feature","properties":[{"gid":"29175"},{"co_cnes":"2320002"},{"lat":"4.34884786605822"},{"long":"-61.1443448066694"},{"no_fantasia":"POSTO DE SAUDE ANDRE FERNANDES"},{"no_logradouro":"RUA PRINCIPAL COMUNIDADE BOCA DA MATA"},{"nu_endereco":"S/N"},{"no_bairro":"CENTRO"},{"nu_telefone":""},{"co_cep":"69345000"},{"uf":"RR"},{"cidade":"Pacaraima"},{"ano_ubs_det":"2016"},{"mes_ubs_det":"5"}],"geometry":{"type":"Point","coordinates":[-61.144344806669,4.3488478660582]}},{"type":"Feature","properties":[{"gid":"29000"},{"co_cnes":"2744449"},{"lat":"2.79781222343437"},{"long":"-60.6830048561079"},{"no_fantasia":"UNIDADE BASICA DE SAUDE 13 DE SETEMBRO"},{"no_logradouro":"AV ELDORADO"},{"nu_endereco":"19"},{"no_bairro":"13 DE SETEMBRO"},{"nu_telefone":"(95)3623 1776"},{"co_cep":"69308000"},{"uf":"RR"},{"cidade":"Boa Vista"},{"ano_ubs_det":"2016"},{"mes_ubs_det":"5"}],"geometry":{"type":"Point","coordinates":[-60.683004856108,2.7978122234344]}},{"type":"Feature","properties":[{"gid":"28838"},{"co_cnes":"2476657"},{"lat":"1.80387124729759"},{"long":"-61.14917687013"},{"no_fantasia":"CENTRO DE SAUDE MANOEL LUIZ RODRIGUES"},{"no_logradouro":"PRACA PE CALLERI"},{"nu_endereco":"S/N"},{"no_bairro":"CENTRO"},{"nu_telefone":"(95)5321226"},{"co_cep":"69360000"},{"uf":"RR"},{"cidade":"Caracaraí"},{"ano_ubs_det":"2016"},{"mes_ubs_det":"5"}],"geometry":{"type":"Point","coordinates":[-61.14917687013,1.8038712472976]}},{"type":"Feature","properties":[{"gid":"29003"},{"co_cnes":"2744511"},{"lat":"2.8238352"},{"long":"-60.7170059"},{"no_fantasia":"UNIDADE BASICA DE SAUDE OLENKA MACELLARO THOME VIEIRA"},{"no_logradouro":"AV MARIO HOMEM DE MELO"},{"nu_endereco":"5075"},{"no_bairro":"CAIMBE"},{"nu_telefone":"(95)36268689"},{"co_cep":"69312155"},{"uf":"RR"},{"cidade":"Boa Vista"},{"ano_ubs_det":"2016"},{"mes_ubs_det":"5"}],"geometry":{"type":"Point","coordinates":[-60.7170059,2.8238352]}},{"type":"Feature","properties":[{"gid":"29010"},{"co_cnes":"2566729"},{"lat":"2.77557134628288"},{"long":"-60.7202339172346"},{"no_fantasia":"UNIDADE BASICA DE SAUDE RAIAR DO SOL"},{"no_logradouro":"RUA DAS ESTRELAS"},{"nu_endereco":"672"},{"no_bairro":"RAIR DO SOL"},{"nu_telefone":"(95)3628 6552"},{"co_cep":"69301970"},{"uf":"RR"},{"cidade":"Boa Vista"},{"ano_ubs_det":"2016"},{"mes_ubs_det":"5"}],"geometry":{"type":"Point","coordinates":[-60.720233917235,2.7755713462829]}},{"type":"Feature","properties":[{"gid":"29007"},{"co_cnes":"2566648"},{"lat":"2.81668191910439"},{"long":"-60.670532672965"},{"no_fantasia":"UNIDADE BASICA DE SAUDE CINTURAO VERDE"},{"no_logradouro":"RUA SANTA CLARA"},{"nu_endereco":"1081"},{"no_bairro":"CINTURAO VERDE"},{"nu_telefone":"(95)36232652"},{"co_cep":"69301970"},{"uf":"RR"},{"cidade":"Boa Vista"},{"ano_ubs_det":"2016"},{"mes_ubs_det":"5"}],"geometry":{"type":"Point","coordinates":[-60.670532672965,2.8166819191044]}},{"type":"Feature","properties":[{"gid":"29009"},{"co_cnes":"2744562"},{"lat":"2.81668191910439"},{"long":"-60.670532672965"},{"no_fantasia":"UNIDADE BASICA DE SAUDE SAO VICENTE"},{"no_logradouro":"AV PRESIDENTE CASTELO BRANCO"},{"nu_endereco":"1875"},{"no_bairro":"SAO VICENTE"},{"nu_telefone":"(95)3623 1556"},{"co_cep":"69301000"},{"uf":"RR"},{"cidade":"Boa Vista"},{"ano_ubs_det":"2016"},{"mes_ubs_det":"5"}],"geometry":{"type":"Point","coordinates":[-60.670532672965,2.8166819191044]}},{"type":"Feature","properties":[{"gid":"29005"},{"co_cnes":"2566753"},{"lat":"2.81668191910439"},{"long":"-60.670532672965"},{"no_fantasia":"UNIDADE BASICA DE SAUDE CARANA"},{"no_logradouro":"RUA VALMIR PEREIRA DA ROCHA"},{"nu_endereco":"98"},{"no_bairro":"CARANA"},{"nu_telefone":"(95) 36267499"},{"co_cep":"69313620"},{"uf":"RR"},{"cidade":"Boa Vista"},{"ano_ubs_det":"2016"},{"mes_ubs_det":"5"}],"geometry":{"type":"Point","coordinates":[-60.670532672965,2.8166819191044]}},{"type":"Feature","properties":[{"gid":"29008"},{"co_cnes":"2566591"},{"lat":"2.80018329620353"},{"long":"-60.7592439651472"},{"no_fantasia":"UNIDADE BASICA DE SAUDE SAYONARA MARIA DANTAS LICARIAO MATOS"},{"no_logradouro":"AVENIDA RAIMUNDO RODRIGUES COELHO"},{"nu_endereco":"2280"},{"no_bairro":"SENADOR HELIO CAMPOS"},{"nu_telefone":"(95) 32248452"},{"co_cep":"69316392"},{"uf":"RR"},{"cidade":"Boa Vista"},{"ano_ubs_det":"2016"},{"mes_ubs_det":"5"}],"geometry":{"type":"Point","coordinates":[-60.759243965147,2.8001832962035]}},{"type":"Feature","properties":[{"gid":"29002"},{"co_cnes":"2744473"},{"lat":"2.8281905"},{"long":"-60.6688629"},{"no_fantasia":"UNIDADE BASICA DE SAUDE BURITIS"},{"no_logradouro":"RUA RAIMUNDO FIGUEIRAS"},{"nu_endereco":"661"},{"no_bairro":"BURITIS"},{"nu_telefone":"(95)3625 7454"},{"co_cep":"69309182"},{"uf":"RR"},{"cidade":"Boa Vista"},{"ano_ubs_det":"2016"},{"mes_ubs_det":"5"}],"geometry":{"type":"Point","coordinates":[-60.6688629,2.8281905]}},{"type":"Feature","properties":[{"gid":"29004"},{"co_cnes":"2744546"},{"lat":"2.8363072872161"},{"long":"-60.7149767875654"},{"no_fantasia":"UNIDADE BASICA DE SAUDE PROF MARIANO DE ANDRADE"},{"no_logradouro":"AVENIDA DECO FONTELIS"},{"nu_endereco":"264"},{"no_bairro":"CARANA"},{"nu_telefone":"(95)3627 1327"},{"co_cep":"69301970"},{"uf":"RR"},{"cidade":"Boa Vista"},{"ano_ubs_det":"2016"},{"mes_ubs_det":"5"}],"geometry":{"type":"Point","coordinates":[-60.714976787565,2.8363072872161]}},{"type":"Feature","properties":[{"gid":"28851"},{"co_cnes":"2657392"},{"lat":"1.67740696795137"},{"long":"-61.0873746871948"},{"no_fantasia":"CENTRO DE SAUDE PETROLINA DO NORTE"},{"no_logradouro":"VILA PETROLINA"},{"nu_endereco":"S/N"},{"no_bairro":"INTERIOR"},{"nu_telefone":""},{"co_cep":"69360000"},{"uf":"RR"},{"cidade":"Caracaraí"},{"ano_ubs_det":"2016"},{"mes_ubs_det":"5"}],"geometry":{"type":"Point","coordinates":[-61.087374687195,1.6774069679514]}},{"type":"Feature","properties":[{"gid":"29011"},{"co_cnes":"2744538"},{"lat":"2.81668191910439"},{"long":"-60.670532672965"},{"no_fantasia":"UNIDADE BASICA DE SAUDE PRICUMA"},{"no_logradouro":"AV VIA DAS FLORES"},{"nu_endereco":"2347"},{"no_bairro":"PRICUMA"},{"nu_telefone":"(95)3625 1007"},{"co_cep":"69301970"},{"uf":"RR"},{"cidade":"Boa Vista"},{"ano_ubs_det":"2016"},{"mes_ubs_det":"5"}],"geometry":{"type":"Point","coordinates":[-60.670532672965,2.8166819191044]}},{"type":"Feature","properties":[{"gid":"29202"},{"co_cnes":"6697402"},{"lat":"0.937195393597556"},{"long":"-60.4250604939819"},{"no_fantasia":"UNIDADE BASICA DE SAUDE ANISIO SILVA"},{"no_logradouro":"RUA MONTE RORAIMA"},{"nu_endereco":"S/N"},{"no_bairro":"NOVO BRASIL"},{"nu_telefone":"(95) 32381926"},{"co_cep":"69373000"},{"uf":"RR"},{"cidade":"Rorainópolis"},{"ano_ubs_det":"2016"},{"mes_ubs_det":"5"}],"geometry":{"type":"Point","coordinates":[-60.425060493982,0.93719539359756]}},{"type":"Feature","properties":[{"gid":"30233"},{"co_cnes":"2566737"},{"lat":"2.82328248023979"},{"long":"-60.7649302482587"},{"no_fantasia":"UNIDADE BASICA DE SAUDE EQUATORIAL"},{"no_logradouro":"RUA FRANCISCO REGIA DE MELO"},{"nu_endereco":"1362"},{"no_bairro":"EQUATORIAL"},{"nu_telefone":"(95) 3628-8772"},{"co_cep":"69301970"},{"uf":"RR"},{"cidade":"Boa Vista"},{"ano_ubs_det":"2016"},{"mes_ubs_det":"5"}],"geometry":{"type":"Point","coordinates":[-60.764930248259,2.8232824802398]}},{"type":"Feature","properties":[{"gid":"30227"},{"co_cnes":"2566400"},{"lat":"2.82"},{"long":"-60.673"},{"no_fantasia":"UNIDADE BASICA DE SAUDE MECEJANA"},{"no_logradouro":"RUA PAVAO"},{"nu_endereco":"932"},{"no_bairro":"MECEANA"},{"nu_telefone":"(95) 3624-2564"},{"co_cep":"69304500"},{"uf":"RR"},{"cidade":"Boa Vista"},{"ano_ubs_det":"2016"},{"mes_ubs_det":"5"}],"geometry":{"type":"Point","coordinates":[-60.673,2.82]}},{"type":"Feature","properties":[{"gid":"30232"},{"co_cnes":"2566583"},{"lat":"2.80677080154411"},{"long":"-60.7519698142988"},{"no_fantasia":"UNIDADE BASICA DE SAUDE SANTA LUZIA"},{"no_logradouro":"RUA JOSE CASIMIRO DA SILVA"},{"nu_endereco":"676"},{"no_bairro":"SANTA LUZIA"},{"nu_telefone":"(95) 3621-6057"},{"co_cep":"69317102"},{"uf":"RR"},{"cidade":"Boa Vista"},{"ano_ubs_det":"2016"},{"mes_ubs_det":"5"}],"geometry":{"type":"Point","coordinates":[-60.751969814299,2.8067708015441]}},{"type":"Feature","properties":[{"gid":"30230"},{"co_cnes":"2566524"},{"lat":"2.82373309135429"},{"long":"-60.7528495788557"},{"no_fantasia":"UNIDADE BASICA DE SAUDE DR DIMITRI RAMOS GRANDEZ DE ARAUJO"},{"no_logradouro":"AV DOS CORRETORE DE IMOVEIS"},{"nu_endereco":"764"},{"no_bairro":"ALVORADA"},{"nu_telefone":"(95) 36274233"},{"co_cep":"69317180"},{"uf":"RR"},{"cidade":"Boa Vista"},{"ano_ubs_det":"2016"},{"mes_ubs_det":"5"}],"geometry":{"type":"Point","coordinates":[-60.752849578856,2.8237330913543]}},{"type":"Feature","properties":[{"gid":"30226"},{"co_cnes":"2566303"},{"lat":"2.84579157829276"},{"long":"-60.7110714912397"},{"no_fantasia":"UNIDADE BASICA DE SAUDE DALMO SILVA FEITOSA"},{"no_logradouro":"RUA AUSTRALIA"},{"nu_endereco":"700"},{"no_bairro":"CAUAME"},{"nu_telefone":"(95) 36285670"},{"co_cep":"69311011"},{"uf":"RR"},{"cidade":"Boa Vista"},{"ano_ubs_det":"2016"},{"mes_ubs_det":"5"}],"geometry":{"type":"Point","coordinates":[-60.71107149124,2.8457915782928]}},{"type":"Feature","properties":[{"gid":"30229"},{"co_cnes":"2566508"},{"lat":"2.82197356224052"},{"long":"-60.7447600364667"},{"no_fantasia":"UNIDADE BASICA DE SAUDE DR SILVIO LEITE"},{"no_logradouro":"RUA VICENTETAVARES DE MELO"},{"nu_endereco":"600"},{"no_bairro":"SILVIO LEITE"},{"nu_telefone":"(95) 36287128"},{"co_cep":"69301000"},{"uf":"RR"},{"cidade":"Boa Vista"},{"ano_ubs_det":"2016"},{"mes_ubs_det":"5"}],"geometry":{"type":"Point","coordinates":[-60.744760036467,2.8219735622405]}},{"type":"Feature","properties":[{"gid":"30231"},{"co_cnes":"2566540"},{"lat":"2.81358361244193"},{"long":"-60.7378506660444"},{"no_fantasia":"UNIDADE BASICA DE SAUDE CAMBARA"},{"no_logradouro":"RUA RAIMUNDO MENDES DE OLIVEIRA"},{"nu_endereco":"16"},{"no_bairro":"CAMBARA"},{"nu_telefone":"(95) 36262361"},{"co_cep":"69313405"},{"uf":"RR"},{"cidade":"Boa Vista"},{"ano_ubs_det":"2016"},{"mes_ubs_det":"5"}],"geometry":{"type":"Point","coordinates":[-60.737850666044,2.8135836124419]}},{"type":"Feature","properties":[{"gid":"30228"},{"co_cnes":"2566451"},{"lat":"2.83156514167777"},{"long":"-60.7336235046369"},{"no_fantasia":"UNIDADE BASICA DE SAUDE SANTA TEREZA"},{"no_logradouro":"RUA ARUANA"},{"nu_endereco":"355"},{"no_bairro":"SANTA TEREZA"},{"nu_telefone":"95-3628-7114"},{"co_cep":"69301970"},{"uf":"RR"},{"cidade":"Boa Vista"},{"ano_ubs_det":"2016"},{"mes_ubs_det":"5"}],"geometry":{"type":"Point","coordinates":[-60.733623504637,2.8315651416778]}},{"type":"Feature","properties":[{"gid":"31843"},{"co_cnes":"3036332"},{"lat":"2.47977223505342"},{"long":"-60.9115185306216"},{"no_fantasia":"UNIDADE BASICA DE SAUDE SABINO PAULO DA SILVA"},{"no_logradouro":"VILA NOVA ESPERANCA SAMAUMA"},{"nu_endereco":"01"},{"no_bairro":"CENTRO"},{"nu_telefone":""},{"co_cep":"69340000"},{"uf":"RR"},{"cidade":"Mucajaí"},{"ano_ubs_det":"2016"},{"mes_ubs_det":"5"}],"geometry":{"type":"Point","coordinates":[-60.911518530622,2.4797722350534]}},{"type":"Feature","properties":[{"gid":"31844"},{"co_cnes":"3036340"},{"lat":"2.81045079231254"},{"long":"-61.4834833145124"},{"no_fantasia":"POSTO DE SAUDE JUSTINO LINHARES ALVES"},{"no_logradouro":"VILA NOVA ESPERANCA"},{"nu_endereco":"001"},{"no_bairro":"CENTRO"},{"nu_telefone":""},{"co_cep":"69340000"},{"uf":"RR"},{"cidade":"Mucajaí"},{"ano_ubs_det":"2016"},{"mes_ubs_det":"5"}],"geometry":{"type":"Point","coordinates":[-61.483483314512,2.8104507923125]}},{"type":"Feature","properties":[{"gid":"33352"},{"co_cnes":"5412161"},{"lat":"1.06108188629147"},{"long":"-59.7854518890364"},{"no_fantasia":"POSTO DE SAUDE NELSON DIAS FERNANDES"},{"no_logradouro":"VICINAL 31"},{"nu_endereco":"S/N"},{"no_bairro":"ZONA RURAL"},{"nu_telefone":"(095) 3235-1229"},{"co_cep":"69375000"},{"uf":"RR"},{"cidade":"São João da Baliza"},{"ano_ubs_det":"2016"},{"mes_ubs_det":"5"}],"geometry":{"type":"Point","coordinates":[-59.785451889036,1.0610818862915]}},{"type":"Feature","properties":[{"gid":"34932"},{"co_cnes":"2589893"},{"lat":"1.80387124729759"},{"long":"-61.14917687013"},{"no_fantasia":"CENTRO DE SAUDE ANFREMON FERREIRA DE FIGUEIREDO"},{"no_logradouro":"AV PRESIDENTE KENNEDY"},{"nu_endereco":"S/N"},{"no_bairro":"NS DO LIVRAMENTO"},{"nu_telefone":"( )"},{"co_cep":"69360000"},{"uf":"RR"},{"cidade":"Caracaraí"},{"ano_ubs_det":"2016"},{"mes_ubs_det":"5"}],"geometry":{"type":"Point","coordinates":[-61.14917687013,1.8038712472976]}},{"type":"Feature","properties":[{"gid":"36259"},{"co_cnes":"3061698"},{"lat":"1.07982516288754"},{"long":"-60.190980434416"},{"no_fantasia":"POSTO DE SAUDE RAIMUNDA DE ARAUJO SILVA"},{"no_logradouro":"RUA GILBERTO LIRA BARBOSA"},{"nu_endereco":"S/N"},{"no_bairro":"CENTRO"},{"nu_telefone":""},{"co_cep":"69370000"},{"uf":"RR"},{"cidade":"São Luiz"},{"ano_ubs_det":"2016"},{"mes_ubs_det":"5"}],"geometry":{"type":"Point","coordinates":[-60.190980434416,1.0798251628875]}},{"type":"Feature","properties":[{"gid":"40084"},{"co_cnes":"2320851"},{"lat":"2.47977223505342"},{"long":"-60.9115185306216"},{"no_fantasia":"UNIDADE BASICA DE SAUDE JOSE RODRIGUES BEZERRA"},{"no_logradouro":"VILA DO APIAU"},{"nu_endereco":"S/N"},{"no_bairro":"CETRO"},{"nu_telefone":""},{"co_cep":"69340000"},{"uf":"RR"},{"cidade":"Mucajaí"},{"ano_ubs_det":"2016"},{"mes_ubs_det":"5"}],"geometry":{"type":"Point","coordinates":[-60.911518530622,2.4797722350534]}},{"type":"Feature","properties":[{"gid":"40083"},{"co_cnes":"2319888"},{"lat":"3.23246955871573"},{"long":"-60.1364350318891"},{"no_fantasia":"UBS TUCANO"},{"no_logradouro":"BR 401"},{"nu_endereco":"S/N"},{"no_bairro":"TUCANO"},{"nu_telefone":""},{"co_cep":"69380000"},{"uf":"RR"},{"cidade":"Bonfim"},{"ano_ubs_det":"2016"},{"mes_ubs_det":"5"}],"geometry":{"type":"Point","coordinates":[-60.136435031889,3.2324695587157]}},{"type":"Feature","properties":[{"gid":"46800"},{"co_cnes":"2319950"},{"lat":"2.89805"},{"long":"-61.49138"},{"no_fantasia":"UNIDADE MISTA BOM SAMARITANO"},{"no_logradouro":"RUA PRINCIPAL"},{"nu_endereco":"S/N"},{"no_bairro":"CENTRO"},{"nu_telefone":""},{"co_cep":"69350000"},{"uf":"RR"},{"cidade":"Alto Alegre"},{"ano_ubs_det":"2016"},{"mes_ubs_det":"5"}],"geometry":{"type":"Point","coordinates":[-61.49138,2.89805]}},{"type":"Feature","properties":[{"gid":"47145"},{"co_cnes":"2476649"},{"lat":"1.82023"},{"long":"-61.13239"},{"no_fantasia":"UNIDADE MISTA DE CARACARAI"},{"no_logradouro":"RUA D 02"},{"nu_endereco":"S/N"},{"no_bairro":"SANTA LUZIA"},{"nu_telefone":"(95) 35321348"},{"co_cep":"69360000"},{"uf":"RR"},{"cidade":"Caracaraí"},{"ano_ubs_det":"2016"},{"mes_ubs_det":"5"}],"geometry":{"type":"Point","coordinates":[-61.13239,1.82023]}},{"type":"Feature","properties":[{"gid":"46801"},{"co_cnes":"2320541"},{"lat":"3.88327"},{"long":"-59.62443"},{"no_fantasia":"UNIDADE MISTA RUTH QUITERIA"},{"no_logradouro":"RUA RUTH QUITERIA"},{"nu_endereco":"07"},{"no_bairro":"CENTRO"},{"nu_telefone":"95 984112797"},{"co_cep":"69355000"},{"uf":"RR"},{"cidade":"Normandia"},{"ano_ubs_det":"2016"},{"mes_ubs_det":"5"}],"geometry":{"type":"Point","coordinates":[-59.62443,3.88327]}},{"type":"Feature","properties":[{"gid":"47146"},{"co_cnes":"2476703"},{"lat":"0.94947"},{"long":"-59.91147"},{"no_fantasia":"UNIDADE MISTA SAO JOAO DA BALIZA"},{"no_logradouro":"AV PERIMENTRAL NORTE"},{"nu_endereco":"S/N"},{"no_bairro":"CENTRO"},{"nu_telefone":"(95)3235-1152"},{"co_cep":"69375000"},{"uf":"RR"},{"cidade":"São João da Baliza"},{"ano_ubs_det":"2016"},{"mes_ubs_det":"5"}],"geometry":{"type":"Point","coordinates":[-59.91147,0.94947]}},{"type":"Feature","properties":[{"gid":"50215"},{"co_cnes":"7576420"},{"lat":"2.8230325"},{"long":"-60.6993348"},{"no_fantasia":"UNIDADE BASICA DE SAUDE LIBERDADE"},{"no_logradouro":"RUA GUILHERME BRITO"},{"nu_endereco":"214"},{"no_bairro":"LIBERDADE"},{"nu_telefone":"36213778"},{"co_cep":"69309075"},{"uf":"RR"},{"cidade":"Boa Vista"},{"ano_ubs_det":"2016"},{"mes_ubs_det":"5"}],"geometry":{"type":"Point","coordinates":[-60.6993348,2.8230325]}},{"type":"Feature","properties":[{"gid":"51044"},{"co_cnes":"7927444"},{"lat":"2.6005122"},{"long":"-62.2626627"},{"no_fantasia":"UNIDADE BASICA DE SAUDE ADILINA MARIA DA CONCEIAO"},{"no_logradouro":"AVENIDA PRINCIPAL"},{"nu_endereco":"S/N"},{"no_bairro":"VOVO JOANA"},{"nu_telefone":""},{"co_cep":"69340000"},{"uf":"RR"},{"cidade":"Mucajaí"},{"ano_ubs_det":"2016"},{"mes_ubs_det":"5"}],"geometry":{"type":"Point","coordinates":[-62.2626627,2.6005122]}},{"type":"Feature","properties":[{"gid":"50519"},{"co_cnes":"7705093"},{"lat":"2.898056"},{"long":"-61.491389"},{"no_fantasia":"POSTO DE SAUDE RECREAR"},{"no_logradouro":"RR205"},{"nu_endereco":"S/N"},{"no_bairro":"ZONA RUARAL"},{"nu_telefone":""},{"co_cep":"69350000"},{"uf":"RR"},{"cidade":"Alto Alegre"},{"ano_ubs_det":"2016"},{"mes_ubs_det":"5"}],"geometry":{"type":"Point","coordinates":[-61.491389,2.898056]}},{"type":"Feature","properties":[{"gid":"185"},{"co_cnes":"4005112"},{"lat":"1.80387124729759"},{"long":"-61.14917687013"},{"no_fantasia":"CENTRO DE SAUDE RENATO COSTA SANTIAGO"},{"no_logradouro":"AV SENADOR HELLIO CAMPOS"},{"nu_endereco":"S/N"},{"no_bairro":"SAO FRANCISCO"},{"nu_telefone":""},{"co_cep":"69360000"},{"uf":"RR"},{"cidade":"Caracaraí"},{"ano_ubs_det":"2016"},{"mes_ubs_det":"5"}],"geometry":{"type":"Point","coordinates":[-61.14917687013,1.8038712472976]}},{"type":"Feature","properties":[{"gid":"688"},{"co_cnes":"2320401"},{"lat":"3.881"},{"long":"-59.623"},{"no_fantasia":"CENTRO DE SAUDE IRACEMA GALVAO"},{"no_logradouro":"AV MAURICIO HABERT"},{"nu_endereco":"S/N"},{"no_bairro":"CENTRO"},{"nu_telefone":"095 3262 1126"},{"co_cep":"69355000"},{"uf":"RR"},{"cidade":"Normandia"},{"ano_ubs_det":"2016"},{"mes_ubs_det":"5"}],"geometry":{"type":"Point","coordinates":[-59.623,3.881]}},{"type":"Feature","properties":[{"gid":"774"},{"co_cnes":"2320916"},{"lat":"2.37242460250848"},{"long":"-61.4377784728986"},{"no_fantasia":"CENTRO DE SAUDE ANA HIPOLITO DOS SANTOS"},{"no_logradouro":"VILA ANTONIO RIBEIRO CAMPOS"},{"nu_endereco":"S/N"},{"no_bairro":"CENTRO"},{"nu_telefone":"(95) 5431101"},{"co_cep":"69348000"},{"uf":"RR"},{"cidade":"Iracema"},{"ano_ubs_det":"2016"},{"mes_ubs_det":"5"}],"geometry":{"type":"Point","coordinates":[-61.437778472899,2.3724246025085]}},{"type":"Feature","properties":[{"gid":"1158"},{"co_cnes":"2744465"},{"lat":"2.81668191910439"},{"long":"-60.670532672965"},{"no_fantasia":"UNIDADE BASICA DE SAUDE ASA BRANCA"},{"no_logradouro":"RUA FRANCISCO CUSTODIO DE ANDRADE"},{"nu_endereco":"505"},{"no_bairro":"ASA BRANCA"},{"nu_telefone":"(95)3626 1754"},{"co_cep":"69312258"},{"uf":"RR"},{"cidade":"Boa Vista"},{"ano_ubs_det":"2016"},{"mes_ubs_det":"5"}],"geometry":{"type":"Point","coordinates":[-60.670532672965,2.8166819191044]}},{"type":"Feature","properties":[{"gid":"253"},{"co_cnes":"7428359"},{"lat":"1.0098504"},{"long":"-60.0423949"},{"no_fantasia":"POSTO DE SAUDE JOAO EVANGELISTA"},{"no_logradouro":"VICINAL 26 KM 50"},{"nu_endereco":"S/N"},{"no_bairro":"ZONA RURAL"},{"nu_telefone":""},{"co_cep":"69370000"},{"uf":"RR"},{"cidade":"São Luiz"},{"ano_ubs_det":"2016"},{"mes_ubs_det":"5"}],"geometry":{"type":"Point","coordinates":[-60.0423949,1.0098504]}},{"type":"Feature","properties":[{"gid":"702"},{"co_cnes":"6571999"},{"lat":"2.84884929656974"},{"long":"-60.7480001449567"},{"no_fantasia":"UNIDADE BASICA DE SAUDE AYGARA MOTTA PEREIRA"},{"no_logradouro":"RUA J"},{"nu_endereco":"256"},{"no_bairro":"CIDADE SATELITE"},{"nu_telefone":"36286943"},{"co_cep":"69301970"},{"uf":"RR"},{"cidade":"Boa Vista"},{"ano_ubs_det":"2016"},{"mes_ubs_det":"5"}],"geometry":{"type":"Point","coordinates":[-60.748000144957,2.8488492965697]}},{"type":"Feature","properties":[{"gid":"1070"},{"co_cnes":"2566729"},{"lat":"2.77557134628288"},{"long":"-60.7202339172346"},{"no_fantasia":"UNIDADE BASICA DE SAUDE RAIAR DO SOL"},{"no_logradouro":"RUA DAS ESTRELAS"},{"nu_endereco":"672"},{"no_bairro":"RAIR DO SOL"},{"nu_telefone":"(95)3628 6552"},{"co_cep":"69301970"},{"uf":"RR"},{"cidade":"Boa Vista"},{"ano_ubs_det":"2016"},{"mes_ubs_det":"5"}],"geometry":{"type":"Point","coordinates":[-60.720233917235,2.7755713462829]}},{"type":"Feature","properties":[{"gid":"1310"},{"co_cnes":"2320029"},{"lat":"3.35028861911031"},{"long":"-59.8780066289099"},{"no_fantasia":"UBS SAO FRANCISCO"},{"no_logradouro":"RUA PRINCIPAL"},{"nu_endereco":"S/N"},{"no_bairro":"VILA SAO FRANCISCO"},{"nu_telefone":"(95)35522004"},{"co_cep":"69380000"},{"uf":"RR"},{"cidade":"Bonfim"},{"ano_ubs_det":"2016"},{"mes_ubs_det":"5"}],"geometry":{"type":"Point","coordinates":[-59.87800662891,3.3502886191103]}},{"type":"Feature","properties":[{"gid":"1887"},{"co_cnes":"2589834"},{"lat":"0.87627768516538"},{"long":"-59.6972823142988"},{"no_fantasia":"CENTRO DE SAUDE CLAITON O DA SILVA"},{"no_logradouro":"RUA AMAZONAS"},{"nu_endereco":"S/N"},{"no_bairro":"CENTRO"},{"nu_telefone":""},{"co_cep":"69378000"},{"uf":"RR"},{"cidade":"Caroebe"},{"ano_ubs_det":"2016"},{"mes_ubs_det":"5"}],"geometry":{"type":"Point","coordinates":[-59.697282314299,0.87627768516538]}}]